virtscreen/__init__.py
virtscreen/__main__.py
virtscreen/display.py
virtscreen/path.py
virtscreen/process.py
virtscreen/qt_backend.py
virtscreen/xrandr.py
virtscreen/assets/AppWindow.qml
virtscreen/assets/DisplayOptionsDialog.qml
virtscreen/assets/DisplayPage.qml
virtscreen/assets/VncOptionsDialog.qml
virtscreen/assets/VncPage.qml
virtscreen/assets/config.default.json
virtscreen/assets/data.json
virtscreen/assets/main.qml
virtscreen/assets/preferenceDialog.qml
virtscreen/icon/full_256x256.png
virtscreen/icon/systray_no_tablet.png
virtscreen/icon/systray_tablet_off.png
virtscreen/icon/systray_tablet_on.png
virtscreen-0.3.1.data/data/share/applications/virtscreen.desktop
virtscreen-0.3.1.data/data/share/icons/virtscreen.png
virtscreen-0.3.1.dist-info/LICENSE.txt
virtscreen-0.3.1.dist-info/METADATA
virtscreen-0.3.1.dist-info/WHEEL
virtscreen-0.3.1.dist-info/entry_points.txt
virtscreen-0.3.1.dist-info/top_level.txt
virtscreen-0.3.1.dist-info/RECORD
