Metadata-Version: 2.1
Name: virtscreen
Version: 0.3.1
Summary: Make your iPad/tablet/computer as a secondary monitor on Linux.
Home-page: https://github.com/kbumsik/VirtScreen
Author: Bumsik Kim
Author-email: k.bumsik@gmail.com
License: UNKNOWN
Project-URL: Bug Reports, https://github.com/kbumsik/VirtScreen/issues
Project-URL: Source, https://github.com/kbumsik/VirtScreen
Project-URL: Author Homepage, https://kbumsik.io
Platform: UNKNOWN
Classifier: Development Status :: 4 - Beta
Classifier: Intended Audience :: Developers
Classifier: Intended Audience :: End Users/Desktop
Classifier: Topic :: Desktop Environment
Classifier: Topic :: Office/Business
Classifier: Topic :: System
Classifier: Topic :: Utilities
Classifier: License :: OSI Approved :: GNU General Public License v3 (GPLv3)
Classifier: Programming Language :: Python :: 3
Classifier: Programming Language :: Python :: 3.6
Classifier: Programming Language :: Python :: 3.7
Classifier: Environment :: X11 Applications
Classifier: Environment :: X11 Applications :: Qt
Classifier: Operating System :: POSIX :: Linux
Classifier: Framework :: AsyncIO
Requires-Python: >=3.6
Requires-Dist: PyQt5 (>=5.10.1)
Requires-Dist: Quamash (>=0.6.0)
Requires-Dist: netifaces (>=0.10.6)
